{
  "Name": "Shadow Generations",
  "Description": "The Shadow expansion of Sonic X Shadow Generations",
  "ReleaseYear": 2024,
  "HedgehogEngine": 2,
  "UsesNTSP": true,
  "BoneOrientation": "XZ",
  "SupportsTopology": true,
  "DataVersions": {
    "SampleChunk": 2,
    "Material": 3,
    "BulletMesh": 3,
    "PointCloud": 2
  },
  "DefaultTextureModes": {
    "diffuse": "sRGB",
    "transparency": "Linear",
    "emission": "Linear",
    "reflection": "Linear",
    "specular": "Linear",
    "normal": "Normal"
  }
}